{"nodes": [{"id": "backend_services_clipboard_py", "label": "clipboard.py", "file_type": "code", "source_file": "backend/services/clipboard.py", "source_location": "L1"}, {"id": "clipboard_clipboardservice", "label": "ClipboardService", "file_type": "code", "source_file": "backend/services/clipboard.py", "source_location": "L14"}, {"id": "clipboard_clipboardservice_read", "label": ".read()", "file_type": "code", "source_file": "backend/services/clipboard.py", "source_location": "L17"}, {"id": "clipboard_clipboardservice_write", "label": ".write()", "file_type": "code", "source_file": "backend/services/clipboard.py", "source_location": "L25"}, {"id": "clipboard_rationale_1", "label": "Jarvis Services \u2014 Clipboard Integration Stub ===================================", "file_type": "rationale", "source_file": "backend/services/clipboard.py", "source_location": "L1"}, {"id": "clipboard_rationale_15", "label": "Read and write the system clipboard.", "file_type": "rationale", "source_file": "backend/services/clipboard.py", "source_location": "L15"}, {"id": "clipboard_rationale_18", "label": "Get the current clipboard content.", "file_type": "rationale", "source_file": "backend/services/clipboard.py", "source_location": "L18"}, {"id": "clipboard_rationale_26", "label": "Set the clipboard content.", "file_type": "rationale", "source_file": "backend/services/clipboard.py", "source_location": "L26"}], "edges": [{"source": "backend_services_clipboard_py", "target": "pyperclip", "relation": "imports", "confidence": "EXTRACTED", "source_file": "backend/services/clipboard.py", "source_location": "L8", "weight": 1.0}, {"source": "backend_services_clipboard_py", "target": "core_logger", "relation": "imports_from", "confidence": "EXTRACTED", "source_file": "backend/services/clipboard.py", "source_location": "L9", "weight": 1.0}, {"source": "backend_services_clipboard_py", "target": "clipboard_clipboardservice", "relation": "contains", "confidence": "EXTRACTED", "source_file": "backend/services/clipboard.py", "source_location": "L14", "weight": 1.0}, {"source": "clipboard_clipboardservice", "target": "clipboard_clipboardservice_read", "relation": "method", "confidence": "EXTRACTED", "source_file": "backend/services/clipboard.py", "source_location": "L17", "weight": 1.0}, {"source": "clipboard_clipboardservice", "target": "clipboard_clipboardservice_write", "relation": "method", "confidence": "EXTRACTED", "source_file": "backend/services/clipboard.py", "source_location": "L25", "weight": 1.0}, {"source": "clipboard_rationale_1", "target": "backend_services_clipboard_py", "relation": "rationale_for", "confidence": "EXTRACTED", "source_file": "backend/services/clipboard.py", "source_location": "L1", "weight": 1.0}, {"source": "clipboard_rationale_15", "target": "clipboard_clipboardservice", "relation": "rationale_for", "confidence": "EXTRACTED", "source_file": "backend/services/clipboard.py", "source_location": "L15", "weight": 1.0}, {"source": "clipboard_rationale_18", "target": "clipboard_clipboardservice_read", "relation": "rationale_for", "confidence": "EXTRACTED", "source_file": "backend/services/clipboard.py", "source_location": "L18", "weight": 1.0}, {"source": "clipboard_rationale_26", "target": "clipboard_clipboardservice_write", "relation": "rationale_for", "confidence": "EXTRACTED", "source_file": "backend/services/clipboard.py", "source_location": "L26", "weight": 1.0}], "raw_calls": [{"caller_nid": "clipboard_clipboardservice_read", "callee": "paste", "source_file": "backend/services/clipboard.py", "source_location": "L20"}, {"caller_nid": "clipboard_clipboardservice_read", "callee": "error", "source_file": "backend/services/clipboard.py", "source_location": "L22"}, {"caller_nid": "clipboard_clipboardservice_write", "callee": "copy", "source_file": "backend/services/clipboard.py", "source_location": "L28"}, {"caller_nid": "clipboard_clipboardservice_write", "callee": "error", "source_file": "backend/services/clipboard.py", "source_location": "L31"}]}